sociallinkfinder/__init__.py
sociallinkfinder/sociallinkfinder.py
sociallinkfinder-0.0.6.dist-info/LICENSE
sociallinkfinder-0.0.6.dist-info/WHEEL
sociallinkfinder-0.0.6.dist-info/METADATA
sociallinkfinder-0.0.6.dist-info/RECORD
