Metadata-Version: 2.1
Name: sociallinkfinder
Version: 0.0.6
Summary: input: company's website url  , output: company's facebook, linkedin, twitter, instagram links in a dictionary
License: MIT
Author: Priyank Mishra
Author-email: priyank.m9320@gmail.com
Requires-Python: >=3.7,<4.0
Classifier: License :: OSI Approved :: MIT License
Classifier: Programming Language :: Python :: 3
Classifier: Programming Language :: Python :: 3.7
Classifier: Programming Language :: Python :: 3.8
Classifier: Programming Language :: Python :: 3.9
Requires-Dist: bs4 (>=0.0.1,<0.0.2)
Requires-Dist: google (>=3.0.0,<4.0.0)
Requires-Dist: rapidfuzz (>=0.13.3,<0.14.0)
Requires-Dist: requests (>=2.25.0,<3.0.0)
